MANIFEST.in
NEWS.txt
README.rst
setup.py
aio_etcd/__init__.py
aio_etcd/auth.py
aio_etcd/client.py
aio_etcd/lock.py
aio_etcd.egg-info/PKG-INFO
aio_etcd.egg-info/SOURCES.txt
aio_etcd.egg-info/dependency_links.txt
aio_etcd.egg-info/not-zip-safe
aio_etcd.egg-info/requires.txt
aio_etcd.egg-info/top_level.txt