Metadata-Version: 1.1
Name: aio-etcd
Version: 0.4.3.1
Summary: An asynchronous python client for etcd
Home-page: http://github.com/M-o-a-T/aio-etcd
Author: Matthias Urlichs
Author-email: matthias@urlichs.de
License: MIT
Keywords: etcd raft distributed log api client
Platform: UNKNOWN
Classifier: Topic :: System :: Distributed Computing
Classifier: Topic :: Software Development :: Libraries
Classifier: License :: OSI Approved :: MIT License
Classifier: Programming Language :: Python :: 3
Classifier: Topic :: Database :: Front-Ends
